abgleich_pkg/__init__.py
abgleich_pkg/abgleich.py
abgleich_pkg/docker/do_csv_upload.sh
abgleich_pkg/docker/docker-compose.yml
abgleich_pkg/input/Abgleich_KUSY_Vorlage.xlsx
tests/__init__.py
tests/t.py
tests/test_one.py
abgleich_pkg_wasix-0.3.14.dist-info/LICENSE.txt
abgleich_pkg_wasix-0.3.14.dist-info/METADATA
abgleich_pkg_wasix-0.3.14.dist-info/WHEEL
abgleich_pkg_wasix-0.3.14.dist-info/top_level.txt
abgleich_pkg_wasix-0.3.14.dist-info/RECORD
