Metadata-Version: 2.1
Name: abgleich-pkg-wasix
Version: 0.3.14
Summary: A small string comparison package
Home-page: https://github.com/wasix01/abgleich-pkg
Author: WasiX
Author-email: wasix01@gmail.com
License: UNKNOWN
Platform: UNKNOWN
Classifier: Programming Language :: Python :: 3
Classifier: License :: OSI Approved :: MIT License
Classifier: Operating System :: OS Independent
Requires-Python: >=3.7
Requires-Dist: csvkit
Requires-Dist: fuzzywuzzy
Requires-Dist: numpy
Requires-Dist: p-tqdm
Requires-Dist: tqdm
Requires-Dist: pandas
Requires-Dist: psycopg2-binary
Requires-Dist: pylint
Requires-Dist: python-Levenshtein
Requires-Dist: SQLAlchemy
Requires-Dist: xlrd
Requires-Dist: psutil
